[
  {
    "id": "25397",
    "name": "Yleistuoli",
    "description": "musta / kromi",
    "price": 29,
    "condition": "Käytetty",
    "imageUrl": "https://offistore.fi/verkkokauppa/img/imagecache/25397_500x500_P0324_022.PNG",
    "category": "tuolit-78?p=4",
    "availability": "5 kpl",
    "productUrl": "https://offistore.fi/verkkokauppa/fin/yleistuoli-p-25397-78",
    "company": "OffiStore"
  },
  {
    "id": "28097",
    "name": "6000/8000 työtuoli",
    "description": "harmaa",
    "price": 189,
    "condition": "Käytetty",
    "imageUrl": "https://offistore.fi/verkkokauppa/img/imagecache/28097_500x500_XTRE24_031.JPEG",
    "category": "tuolit-78?p=4",
    "availability": "4 kpl",
    "productUrl": "https://offistore.fi/verkkokauppa/fin/6000_8000_tyotuoli-p-28097-78",
    "company": "OffiStore"
  },
  {
    "id": "23239",
    "name": "AC5 - Neuvottelutuoli pyörillä",
    "description": "harmaa / kromi",
    "price": 94,
    "condition": "Käytetty",
    "imageUrl": "https://offistore.fi/verkkokauppa/img/imagecache/23239_500x500_PKTT1023_065.PNG",
    "category": "tuolit-78?p=4",
    "availability": "4 kpl",
    "productUrl": "https://offistore.fi/verkkokauppa/fin/ac5_neuvottelutuoli_pyorilla-p-23239-78",
    "company": "OffiStore"
  },
  {
    "id": "21341",
    "name": "Aino - asiakastuoli",
    "description": "punainen / musta",
    "price": 30,
    "condition": "Käytetty",
    "imageUrl": "https://offistore.fi/verkkokauppa/img/imagecache/21341_500x500_XPP250523_001.JPEG",
    "category": "tuolit-78?p=4",
    "availability": "4 kpl",
    "productUrl": "https://offistore.fi/verkkokauppa/fin/aino_asiakastuoli-p-21341-78",
    "company": "OffiStore"
  },
  {
    "id": "23183",
    "name": "Asiakastuoli",
    "description": "violetti / valkoinen",
    "price": 45,
    "condition": "Käytetty",
    "imageUrl": "https://offistore.fi/verkkokauppa/img/imagecache/23183_500x500_Y-TL1503_168.PNG",
    "category": "tuolit-78?p=4",
    "availability": "4 kpl",
    "productUrl": "https://offistore.fi/verkkokauppa/fin/asiakastuoli-p-23183-78",
    "company": "OffiStore"
  },
  {
    "id": "23891",
    "name": "Bernhard - yleistuoli",
    "description": "keltainen",
    "price": 35,
    "condition": "Käytetty",
    "imageUrl": "https://offistore.fi/verkkokauppa/img/imagecache/23891_500x500_IMG_20231208_115820.png",
    "category": "tuolit-78?p=4",
    "availability": "4 kpl",
    "productUrl": "https://offistore.fi/verkkokauppa/fin/bernhard_yleistuoli-p-23891-78",
    "company": "OffiStore"
  },
  {
    "id": "19746",
    "name": "Catifa - tuoli",
    "description": "valkoinen / ruskea",
    "price": 39,
    "condition": "Käytetty",
    "imageUrl": "https://offistore.fi/verkkokauppa/img/imagecache/19746_500x500_XDB06223_217.JPEG",
    "category": "tuolit-78?p=4",
    "availability": "4 kpl",
    "productUrl": "https://offistore.fi/verkkokauppa/fin/catifa_tuoli-p-19746-78",
    "company": "OffiStore"
  },
  {
    "id": "27993",
    "name": "Fondo Korkea jakkara",
    "description": "harmaa / valkoinen",
    "price": 49,
    "condition": "Käytetty",
    "imageUrl": "https://offistore.fi/verkkokauppa/img/imagecache/27993_500x500_POUL124_770.JPEG",
    "category": "tuolit-78?p=4",
    "availability": "4 kpl",
    "productUrl": "https://offistore.fi/verkkokauppa/fin/fondo_korkea_jakkara-p-27993-78",
    "company": "OffiStore"
  },
  {
    "id": "25630",
    "name": "LAB - Neuvottelutuoli pyörillä",
    "description": "vihreä / valkoinen",
    "price": 75,
    "condition": "Käytetty",
    "imageUrl": "https://offistore.fi/verkkokauppa/img/imagecache/25630_500x500_P0324_047.PNG",
    "category": "tuolit-78?p=4",
    "availability": "4 kpl",
    "productUrl": "https://offistore.fi/verkkokauppa/fin/lab_neuvottelutuoli_pyorilla-p-25630-78",
    "company": "OffiStore"
  },
  {
    "id": "26917",
    "name": "Neuvottelutuoli, verkko",
    "description": "musta",
    "price": 75,
    "condition": "Käytetty",
    "imageUrl": "https://offistore.fi/verkkokauppa/img/imagecache/26917_500x500_XTRE24_008.JPEG",
    "category": "tuolit-78?p=4",
    "availability": "4 kpl",
    "productUrl": "https://offistore.fi/verkkokauppa/fin/neuvottelutuoli_verkko-p-26917-78",
    "company": "OffiStore"
  },
  {
    "id": "24690",
    "name": "Picco-yleistuoli, istuinverhoilu",
    "description": "koivu / punainen",
    "price": 35,
    "condition": "Käytetty",
    "imageUrl": "https://offistore.fi/verkkokauppa/img/imagecache/24690_500x500_Offi-pohja---MR21_11_23-PhotoRoom-6.png",
    "category": "tuolit-78?p=4",
    "availability": "4 kpl",
    "productUrl": "https://offistore.fi/verkkokauppa/fin/picco_yleistuoli_istuinverhoilu-p-24690-78",
    "company": "OffiStore"
  },
  {
    "id": "24576",
    "name": "Pro 20 työtuoli, +kn",
    "description": "sininen / kromi",
    "price": 189,
    "condition": "Käytetty",
    "imageUrl": "https://offistore.fi/verkkokauppa/img/imagecache/24576_500x500_PhotoRoom-20240117_141111.png",
    "category": "tuolit-78?p=4",
    "availability": "4 kpl",
    "productUrl": "https://offistore.fi/verkkokauppa/fin/pro_20_tyotuoli_kn-p-24576-78",
    "company": "OffiStore"
  },
  {
    "id": "26232",
    "name": "Rocket - Jakkara",
    "description": "musta",
    "price": 169,
    "condition": "Käytetty",
    "imageUrl": "https://offistore.fi/verkkokauppa/img/imagecache/26232_500x500_P0424_027.PNG",
    "category": "tuolit-78?p=4",
    "availability": "4 kpl",
    "productUrl": "https://offistore.fi/verkkokauppa/fin/rocket_jakkara-p-26232-78",
    "company": "OffiStore"
  },
  {
    "id": "27398",
    "name": "Select - Neuvottelutuoli",
    "description": "ruskea / harmaa",
    "price": 89,
    "condition": "Käytetty",
    "imageUrl": "https://offistore.fi/verkkokauppa/img/imagecache/27398_500x500_P0624_009.PNG",
    "category": "tuolit-78?p=4",
    "availability": "4 kpl",
    "productUrl": "https://offistore.fi/verkkokauppa/fin/select_neuvottelutuoli-p-27398-78",
    "company": "OffiStore"
  },
  {
    "id": "28446",
    "name": "Signum asiakastuoli käsinojilla",
    "description": "sininen / tumman harmaa",
    "price": 49,
    "condition": "Käytetty",
    "imageUrl": "https://offistore.fi/verkkokauppa/img/imagecache/28446_500x500_XKOK24_003.JPEG",
    "category": "tuolit-78?p=4",
    "availability": "4 kpl",
    "productUrl": "https://offistore.fi/verkkokauppa/fin/signum_asiakastuoli_kasinojilla-p-28446-78",
    "company": "OffiStore"
  },
  {
    "id": "17288",
    "name": "Soft X neuvottelutuoli",
    "description": "punainen / kromi",
    "price": 138.33,
    "condition": "Käytetty",
    "imageUrl": "https://offistore.fi/verkkokauppa/img/imagecache/17288_500x500_PMV050922_176.PNG",
    "category": "tuolit-78?p=4",
    "availability": "4 kpl",
    "productUrl": "https://offistore.fi/verkkokauppa/fin/soft_x_neuvottelutuoli-p-17288-78",
    "company": "OffiStore"
  },
  {
    "id": "19286",
    "name": "Sola - jakkara",
    "description": "turkoosi / valkoinen",
    "price": 49,
    "condition": "Käytetty",
    "imageUrl": "https://offistore.fi/verkkokauppa/img/imagecache/19286_500x500_XPPRTA020123_236.JPEG",
    "category": "tuolit-78?p=4",
    "availability": "4 kpl",
    "productUrl": "https://offistore.fi/verkkokauppa/fin/sola_jakkara-p-19286-78",
    "company": "OffiStore"
  },
  {
    "id": "22155",
    "name": "Sola- tuoli",
    "description": "vihreä / kromi",
    "price": 30,
    "condition": "Käytetty",
    "imageUrl": "https://offistore.fi/verkkokauppa/img/imagecache/22155_500x500_XPP260623_002.PNG",
    "category": "tuolit-78?p=4",
    "availability": "4 kpl",
    "productUrl": "https://offistore.fi/verkkokauppa/fin/sola_tuoli-p-22155-78",
    "company": "OffiStore"
  },
  {
    "id": "28787",
    "name": "Tuoli",
    "description": "harmaa",
    "price": 39,
    "condition": "Käytetty",
    "imageUrl": "https://offistore.fi/verkkokauppa/img/imagecache/28787_500x500_PTRE124_623.JPEG",
    "category": "tuolit-78?p=4",
    "availability": "4 kpl",
    "productUrl": "https://offistore.fi/verkkokauppa/fin/tuoli-p-28787-78",
    "company": "OffiStore"
  },
  {
    "id": "28583",
    "name": "Verkkoselkäinen työtuoli +kn",
    "description": "musta / harmaa",
    "price": 179,
    "condition": "Käytetty",
    "imageUrl": "https://offistore.fi/verkkokauppa/img/imagecache/28583_500x500_P0924_020.PNG",
    "category": "tuolit-78?p=4",
    "availability": "4 kpl",
    "productUrl": "https://offistore.fi/verkkokauppa/fin/verkkoselkainen_tyotuoli_kn-p-28583-78",
    "company": "OffiStore"
  },
  {
    "id": "24903",
    "name": "Viv Wood - yleistuoli",
    "description": "punainen / tammi",
    "price": 49,
    "condition": "Käytetty",
    "imageUrl": "https://offistore.fi/verkkokauppa/img/imagecache/24903_500x500_P0224_013.PNG",
    "category": "tuolit-78?p=4",
    "availability": "4 kpl",
    "productUrl": "https://offistore.fi/verkkokauppa/fin/viv_wood_yleistuoli-p-24903-78",
    "company": "OffiStore"
  },
  {
    "id": "24902",
    "name": "Viv Wood - yleistuoli",
    "description": "harmaa / tammi",
    "price": 49,
    "condition": "Käytetty",
    "imageUrl": "https://offistore.fi/verkkokauppa/img/imagecache/24902_500x500_P0224_014.PNG",
    "category": "tuolit-78?p=4",
    "availability": "4 kpl",
    "productUrl": "https://offistore.fi/verkkokauppa/fin/viv_wood_yleistuoli-p-24902-78",
    "company": "OffiStore"
  },
  {
    "id": "23314",
    "name": "6000 - työtuoli",
    "description": "sininen / musta",
    "price": 189,
    "condition": "Käytetty",
    "imageUrl": "https://offistore.fi/verkkokauppa/img/imagecache/23314_500x500_PKTT_TRE1023_105.JPEG",
    "category": "tuolit-78?p=4",
    "availability": "3 kpl",
    "productUrl": "https://offistore.fi/verkkokauppa/fin/6000_tyotuoli-p-23314-78",
    "company": "OffiStore"
  },
  {
    "id": "25663",
    "name": "Aktiivituoli",
    "description": "oranssi",
    "price": 189,
    "condition": "Käytetty",
    "imageUrl": "https://offistore.fi/verkkokauppa/img/imagecache/25663_500x500_PTRE124_531.JPEG",
    "category": "tuolit-78?p=4",
    "availability": "3 kpl",
    "productUrl": "https://offistore.fi/verkkokauppa/fin/aktiivituoli-p-25663-78",
    "company": "OffiStore"
  },
  {
    "id": "28052",
    "name": "Form tuoli",
    "description": "punainen / pyökki",
    "price": 179,
    "condition": "Käytetty",
    "imageUrl": "https://offistore.fi/verkkokauppa/img/imagecache/28052_500x500_XTRE24_024.JPEG",
    "category": "tuolit-78?p=4",
    "availability": "3 kpl",
    "productUrl": "https://offistore.fi/verkkokauppa/fin/form_tuoli-p-28052-78",
    "company": "OffiStore"
  },
  {
    "id": "28048",
    "name": "Form tuoli",
    "description": "harmaa / pyökki",
    "price": 179,
    "condition": "Käytetty",
    "imageUrl": "https://offistore.fi/verkkokauppa/img/imagecache/28048_500x500_XTRE24_020.JPEG",
    "category": "tuolit-78?p=4",
    "availability": "3 kpl",
    "productUrl": "https://offistore.fi/verkkokauppa/fin/form_tuoli-p-28048-78",
    "company": "OffiStore"
  },
  {
    "id": "24086",
    "name": "James - työtuoli",
    "description": "vihreä / musta",
    "price": 139,
    "condition": "Käytetty",
    "imageUrl": "https://offistore.fi/verkkokauppa/img/imagecache/24086_500x500_P0124_031.PNG",
    "category": "tuolit-78?p=4",
    "availability": "3 kpl",
    "productUrl": "https://offistore.fi/verkkokauppa/fin/james_tyotuoli-p-24086-78",
    "company": "OffiStore"
  },
  {
    "id": "27394",
    "name": "Meetingframe - neuvottelutuoli",
    "description": "harmaa / kromi",
    "price": 75,
    "condition": "Käytetty",
    "imageUrl": "https://offistore.fi/verkkokauppa/img/imagecache/27394_500x500_P0624_013.PNG",
    "category": "tuolit-78?p=4",
    "availability": "3 kpl",
    "productUrl": "https://offistore.fi/verkkokauppa/fin/meetingframe_neuvottelutuoli-p-27394-78",
    "company": "OffiStore"
  },
  {
    "id": "20010",
    "name": "Neuvottelutuoli",
    "description": "musta / kromi",
    "price": 125,
    "condition": "Käytetty",
    "imageUrl": "https://offistore.fi/verkkokauppa/img/imagecache/20010_500x500_XDB210223_202.JPEG",
    "category": "tuolit-78?p=4",
    "availability": "3 kpl",
    "productUrl": "https://offistore.fi/verkkokauppa/fin/neuvottelutuoli-p-20010-78",
    "company": "OffiStore"
  },
  {
    "id": "20138",
    "name": "Asiakastuoli",
    "description": "musta / harmaa",
    "price": 40,
    "condition": "Käytetty",
    "imageUrl": "https://offistore.fi/verkkokauppa/img/imagecache/20138_500x500_XPP140323_008.PNG",
    "category": "tuolit-78?p=4",
    "availability": "2 kpl",
    "productUrl": "https://offistore.fi/verkkokauppa/fin/asiakastuoli-p-20138-78",
    "company": "OffiStore"
  },
  {
    "id": "28057",
    "name": "Form tuoli",
    "description": "tumman harmaa / pyökki",
    "price": 179,
    "condition": "Käytetty",
    "imageUrl": "https://offistore.fi/verkkokauppa/img/imagecache/28057_500x500_XTRE24_029.JPEG",
    "category": "tuolit-78?p=4",
    "availability": "2 kpl",
    "productUrl": "https://offistore.fi/verkkokauppa/fin/form_tuoli-p-28057-78",
    "company": "OffiStore"
  },
  {
    "id": "28055",
    "name": "Form tuoli",
    "description": "eri värejä / pyökki",
    "price": 179,
    "condition": "Käytetty",
    "imageUrl": "https://offistore.fi/verkkokauppa/img/imagecache/28055_500x500_XTRE24_027.JPEG",
    "category": "tuolit-78?p=4",
    "availability": "2 kpl",
    "productUrl": "https://offistore.fi/verkkokauppa/fin/form_tuoli-p-28055-78",
    "company": "OffiStore"
  },
  {
    "id": "28044",
    "name": "Form tuoli",
    "description": "violetti / pyökki",
    "price": 179,
    "condition": "Käytetty",
    "imageUrl": "https://offistore.fi/verkkokauppa/img/imagecache/28044_500x500_XTRE24_030.JPEG",
    "category": "tuolit-78?p=4",
    "availability": "2 kpl",
    "productUrl": "https://offistore.fi/verkkokauppa/fin/form_tuoli-p-28044-78",
    "company": "OffiStore"
  },
  {
    "id": "23103",
    "name": "Futu 1020 - työtuoli",
    "description": "musta / musta",
    "price": 143,
    "condition": "Käytetty",
    "imageUrl": "https://offistore.fi/verkkokauppa/img/imagecache/23103_500x500_PKTT_TRE1023_056.JPEG",
    "category": "tuolit-78?p=4",
    "availability": "2 kpl",
    "productUrl": "https://offistore.fi/verkkokauppa/fin/futu_1020_tyotuoli-p-23103-78",
    "company": "OffiStore"
  },
  {
    "id": "24574",
    "name": "James työtuoli, +kn",
    "description": "sininen / musta",
    "price": 255,
    "condition": "Käytetty",
    "imageUrl": "https://offistore.fi/verkkokauppa/img/imagecache/24574_500x500_PhotoRoom-20240117_140904.png",
    "category": "tuolit-78?p=4",
    "availability": "2 kpl",
    "productUrl": "https://offistore.fi/verkkokauppa/fin/james_tyotuoli_kn-p-24574-78",
    "company": "OffiStore"
  },
  {
    "id": "25116",
    "name": "Neuvottelutuoli pyörillä",
    "description": "harmaa / musta",
    "price": 65,
    "condition": "Käytetty",
    "imageUrl": "https://offistore.fi/verkkokauppa/img/imagecache/25116_500x500_P0224_107.PNG",
    "category": "tuolit-78?p=4",
    "availability": "2 kpl",
    "productUrl": "https://offistore.fi/verkkokauppa/fin/neuvottelutuoli_pyorilla-p-25116-78",
    "company": "OffiStore"
  },
  {
    "id": "28444",
    "name": "Sally yleistuoli",
    "description": "musta / musta",
    "price": 45,
    "condition": "Käytetty",
    "imageUrl": "https://offistore.fi/verkkokauppa/img/imagecache/28444_500x500_XKOK24_006.JPEG",
    "category": "tuolit-78?p=4",
    "availability": "2 kpl",
    "productUrl": "https://offistore.fi/verkkokauppa/fin/sally_yleistuoli-p-28444-78",
    "company": "OffiStore"
  },
  {
    "id": "24570",
    "name": "Step työtuoli, +kn",
    "description": "sininen / harmaa",
    "price": 195,
    "condition": "Käytetty",
    "imageUrl": "https://offistore.fi/verkkokauppa/img/imagecache/24570_500x500_PhotoRoom-20240117_140710.png",
    "category": "tuolit-78?p=4",
    "availability": "2 kpl",
    "productUrl": "https://offistore.fi/verkkokauppa/fin/step_tyotuoli_kn-p-24570-78",
    "company": "OffiStore"
  },
  {
    "id": "30099",
    "name": "Työtuoli Axia + kn + nt",
    "description": "punainen / musta",
    "price": 345,
    "condition": "Käytetty",
    "imageUrl": "https://offistore.fi/verkkokauppa/img/imagecache/30099_500x500_XTRE24_107.JPEG",
    "category": "tuolit-78?p=4",
    "availability": "2 kpl",
    "productUrl": "https://offistore.fi/verkkokauppa/fin/tyotuoli_axia_kn_nt-p-30099-78",
    "company": "OffiStore"
  },
  {
    "id": "20566",
    "name": "Yleistuoli",
    "description": "valkoinen / punainen",
    "price": 39,
    "condition": "Käytetty",
    "imageUrl": "https://offistore.fi/verkkokauppa/img/imagecache/20566_500x500_ZTL1503_137.JPEG",
    "category": "tuolit-78?p=4",
    "availability": "2 kpl",
    "productUrl": "https://offistore.fi/verkkokauppa/fin/yleistuoli-p-20566-78",
    "company": "OffiStore"
  },
  {
    "id": "21002",
    "name": "Still työtuoli M/H",
    "description": "harmaa / kromi",
    "price": 189,
    "condition": "Käytetty",
    "imageUrl": "https://offistore.fi/verkkokauppa/img/imagecache/21002_500x500_XEY2903_002.JPEG",
    "category": "tuolit-78?p=4",
    "availability": "1 kpl",
    "productUrl": "https://offistore.fi/verkkokauppa/fin/still_tyotuoli_m_h-p-21002-78",
    "company": "OffiStore"
  },
  {
    "id": "26661",
    "name": "6/8 työtuoli uudelleen verhoiltu, pyöreä selkä",
    "description": "Kinnarps",
    "price": 269,
    "condition": "Käytetty",
    "imageUrl": "https://offistore.fi/verkkokauppa/img/imagecache/26661_500x500_X68PY%C3%96_VERHOILTU.JPEG",
    "category": "tuolit-78?p=4",
    "availability": "1 kpl",
    "productUrl": "https://offistore.fi/verkkokauppa/fin/6_8_tyotuoli_uudelleen_verhoiltu_pyorea_selka-p-26661-78",
    "company": "OffiStore"
  }
]
